pg_dump_anonymized/__init__.py
pg_dump_anonymized/_version.py
pg_dump_anonymized/bk_anonymized.py
pg_dump_anonymized/command_basic.py
pg_dump_anonymized-0.1.0.dist-info/LICENSE
pg_dump_anonymized-0.1.0.dist-info/METADATA
pg_dump_anonymized-0.1.0.dist-info/WHEEL
pg_dump_anonymized-0.1.0.dist-info/top_level.txt
pg_dump_anonymized-0.1.0.dist-info/RECORD
