Metadata-Version: 2.1
Name: pg-dump-anonymized
Version: 0.1.0
Summary: anonymize database (gist, basic goal: auth_user table for pg_dump)
Home-page: https://github.com/pyutil/pg-dump-anonymized
Author: Mirek Zvolský
Author-email: zvolsky@seznam.cz
License: MIT
Download-URL: https://github.com/pyutil/pg-dump-anonymized/archive/0.1.0.tar.gz
Keywords: pg-dump-anonymized
Platform: UNKNOWN
Classifier: Development Status :: 4 - Beta
Classifier: Framework :: Django :: 1.11
Classifier: Framework :: Django :: 2.2
Classifier: Framework :: Django :: 3.0
Classifier: Intended Audience :: Developers
Classifier: License :: OSI Approved :: BSD License
Classifier: Natural Language :: English
Classifier: Programming Language :: Python :: 3
Classifier: Programming Language :: Python :: 3.6
Classifier: Programming Language :: Python :: 3.7
Classifier: Programming Language :: Python :: 3.8
